json_rpc_scan/__init__.py
json_rpc_scan/__main__.py
json_rpc_scan/__version__.py
json_rpc_scan/client.py
json_rpc_scan/compat.py
json_rpc_scan/config.py
json_rpc_scan/diff.py
json_rpc_scan/py.typed
json_rpc_scan/runners/__init__.py
json_rpc_scan/runners/base.py
json_rpc_scan/runners/debug.py
json_rpc_scan/runners/eth.py
json_rpc_scan/runners/trace.py
json_rpc_scan-0.1.0.dist-info/METADATA
json_rpc_scan-0.1.0.dist-info/WHEEL
json_rpc_scan-0.1.0.dist-info/entry_points.txt
json_rpc_scan-0.1.0.dist-info/licenses/LICENSE
json_rpc_scan-0.1.0.dist-info/RECORD
