Metadata-Version: 2.4
Name: json-rpc-scan
Version: 0.1.0
Summary: Scans Ethereum (EVM) Blocks via JSON-RPC and looks for client diffs
Project-URL: Homepage, https://github.com/MysticRyuujin/json-rpc-scan
Project-URL: Repository, https://github.com/MysticRyuujin/json-rpc-scan
Project-URL: Issues, https://github.com/MysticRyuujin/json-rpc-scan/issues
Author: Chase Wright
License: MIT
License-File: LICENSE
Keywords: blockchain,diff,ethereum,evm,json-rpc
Classifier: Development Status :: 3 - Alpha
Classifier: Environment :: Console
Classifier: Intended Audience :: Developers
Classifier: License :: OSI Approved :: MIT License
Classifier: Operating System :: OS Independent
Classifier: Programming Language :: Python :: 3
Classifier: Programming Language :: Python :: 3 :: Only
Classifier: Programming Language :: Python :: 3.13
Classifier: Topic :: Software Development :: Testing
Classifier: Typing :: Typed
Requires-Python: >=3.13
Requires-Dist: httpx>=0.28.0
Requires-Dist: pyyaml>=6.0
Requires-Dist: tqdm>=4.67.0
Provides-Extra: dev
Requires-Dist: black>=25.0.0; extra == 'dev'
Requires-Dist: mypy>=1.19.0; extra == 'dev'
Requires-Dist: pre-commit>=4.5.0; extra == 'dev'
Requires-Dist: pytest-asyncio>=1.0.0; extra == 'dev'
Requires-Dist: pytest-cov>=7.0.0; extra == 'dev'
Requires-Dist: pytest>=9.0.0; extra == 'dev'
Requires-Dist: ruff>=0.14.0; extra == 'dev'
Requires-Dist: types-pyyaml>=6.0.0; extra == 'dev'
Requires-Dist: types-tqdm>=4.67.0; extra == 'dev'
